[
  {
    "answer": "DANGER",
    "clueType": "anagram",
    "difficulty": 2,
    "clue": "Hazard from garden, developed (6)",
    "def": {
      "text": "Hazard",
      "position": "start"
    },
    "wordplay": {
      "indicator": "developed",
      "fodder": "garden",
      "operations": [
        {
          "op": "anagram",
          "input": "GARDEN",
          "output": "DANGER"
        }
      ]
    },
    "parse": "(GARDEN)* = DANGER, a hazard."
  },
  {
    "answer": "SACRED",
    "clueType": "anagram",
    "difficulty": 2,
    "clue": "Holy cedars chopped down (6)",
    "def": {
      "text": "Holy",
      "position": "start"
    },
    "wordplay": {
      "indicator": "chopped",
      "fodder": "cedars",
      "operations": [
        {
          "op": "anagram",
          "input": "CEDARS",
          "output": "SACRED"
        }
      ]
    },
    "parse": "(CEDARS)* = SACRED, meaning holy."
  },
  {
    "answer": "STREAM",
    "clueType": "anagram",
    "difficulty": 2,
    "clue": "Circus tamers organised a flow of water (6)",
    "def": {
      "text": "flow of water",
      "position": "end"
    },
    "wordplay": {
      "indicator": "organised",
      "fodder": "Tamers",
      "operations": [
        {
          "op": "anagram",
          "input": "TAMERS",
          "output": "STREAM"
        }
      ]
    },
    "parse": "(TAMERS)* = STREAM, a flow of water."
  },
  {
    "answer": "SILENT",
    "clueType": "anagram",
    "difficulty": 2,
    "clue": "Quiet as the fans listen wildly (6)",
    "def": {
      "text": "Quiet",
      "position": "start"
    },
    "wordplay": {
      "indicator": "wildly",
      "fodder": "listen",
      "operations": [
        {
          "op": "anagram",
          "input": "LISTEN",
          "output": "SILENT"
        }
      ]
    },
    "parse": "(LISTEN)* = SILENT, meaning quiet."
  },
  {
    "answer": "DEARTH",
    "clueType": "anagram",
    "difficulty": 2,
    "clue": "Hatred turned into shortage (6)",
    "def": {
      "text": "shortage",
      "position": "end"
    },
    "wordplay": {
      "indicator": "turned",
      "fodder": "hatred",
      "operations": [
        {
          "op": "anagram",
          "input": "HATRED",
          "output": "DEARTH"
        }
      ]
    },
    "parse": "(HATRED)* = DEARTH, a shortage."
  },
  {
    "answer": "RESCUE",
    "clueType": "anagram",
    "difficulty": 2,
    "clue": "Secure, somehow, a saving (6)",
    "def": {
      "text": "saving",
      "position": "end"
    },
    "wordplay": {
      "indicator": "confused",
      "fodder": "secure",
      "operations": [
        {
          "op": "anagram",
          "input": "SECURE",
          "output": "RESCUE"
        }
      ]
    },
    "parse": "(SECURE)* = RESCUE, a saving."
  },
  {
    "answer": "GARDEN",
    "clueType": "anagram",
    "difficulty": 2,
    "clue": "Danger out of control in the plot (6)",
    "def": {
      "text": "plot",
      "position": "end"
    },
    "wordplay": {
      "indicator": "out of control",
      "fodder": "Danger",
      "operations": [
        {
          "op": "anagram",
          "input": "DANGER",
          "output": "GARDEN"
        }
      ]
    },
    "parse": "(DANGER)* = GARDEN, a plot."
  },
  {
    "answer": "LISTEN",
    "clueType": "anagram",
    "difficulty": 2,
    "clue": "Attend to tinsel, scattered about (6)",
    "def": {
      "text": "Attend to",
      "position": "start"
    },
    "wordplay": {
      "indicator": "scattered",
      "fodder": "tinsel",
      "operations": [
        {
          "op": "anagram",
          "input": "TINSEL",
          "output": "LISTEN"
        }
      ]
    },
    "parse": "(TINSEL)* = LISTEN, to attend to."
  },
  {
    "answer": "CARPET",
    "clueType": "charade",
    "difficulty": 2,
    "clue": "Vehicle the animal lies on, the floor covering (6)",
    "def": {
      "text": "floor covering",
      "position": "end"
    },
    "wordplay": {
      "indicator": "",
      "operations": [
        {
          "op": "synonym",
          "input": "Vehicle",
          "output": "CAR"
        },
        {
          "op": "synonym",
          "input": "animal",
          "output": "PET"
        },
        {
          "op": "concat",
          "input": "CAR+PET",
          "output": "CARPET"
        }
      ]
    },
    "parse": "CAR (vehicle) + PET (animal) = CARPET, a floor covering."
  },
  {
    "answer": "PANTRY",
    "clueType": "charade",
    "difficulty": 2,
    "clue": "Cooking vessel's attempt at the larder (6)",
    "def": {
      "text": "larder",
      "position": "end"
    },
    "wordplay": {
      "indicator": "",
      "operations": [
        {
          "op": "synonym",
          "input": "Cooking vessel",
          "output": "PAN"
        },
        {
          "op": "synonym",
          "input": "attempt",
          "output": "TRY"
        },
        {
          "op": "concat",
          "input": "PAN+TRY",
          "output": "PANTRY"
        }
      ]
    },
    "parse": "PAN (cooking vessel) + TRY (attempt) = PANTRY, a larder."
  },
  {
    "answer": "OUTFIT",
    "clueType": "charade",
    "difficulty": 2,
    "clue": "Not at home but in good shape, sporting a costume (6)",
    "def": {
      "text": "costume",
      "position": "end"
    },
    "wordplay": {
      "indicator": "",
      "operations": [
        {
          "op": "synonym",
          "input": "Not at home",
          "output": "OUT"
        },
        {
          "op": "synonym",
          "input": "in good shape",
          "output": "FIT"
        },
        {
          "op": "concat",
          "input": "OUT+FIT",
          "output": "OUTFIT"
        }
      ]
    },
    "parse": "OUT (not at home) + FIT (in good shape) = OUTFIT, a costume."
  },
  {
    "answer": "HATRED",
    "clueType": "charade",
    "difficulty": 2,
    "clue": "Headgear in communist's loathing (6)",
    "def": {
      "text": "loathing",
      "position": "end"
    },
    "wordplay": {
      "indicator": "",
      "operations": [
        {
          "op": "synonym",
          "input": "Headgear",
          "output": "HAT"
        },
        {
          "op": "synonym",
          "input": "communist",
          "output": "RED"
        },
        {
          "op": "concat",
          "input": "HAT+RED",
          "output": "HATRED"
        }
      ]
    },
    "parse": "HAT (headgear) + RED (communist) = HATRED, loathing."
  },
  {
    "answer": "MANAGE",
    "clueType": "charade",
    "difficulty": 2,
    "clue": "Chap getting older to run things (6)",
    "def": {
      "text": "run things",
      "position": "end"
    },
    "wordplay": {
      "indicator": "",
      "operations": [
        {
          "op": "synonym",
          "input": "Chap",
          "output": "MAN"
        },
        {
          "op": "synonym",
          "input": "getting older",
          "output": "AGE"
        },
        {
          "op": "concat",
          "input": "MAN+AGE",
          "output": "MANAGE"
        }
      ]
    },
    "parse": "MAN (chap) + AGE (getting older) = MANAGE, to run things."
  },
  {
    "answer": "FORGET",
    "clueType": "charade",
    "difficulty": 2,
    "clue": "In favour of acquiring something to overlook (6)",
    "def": {
      "text": "overlook",
      "position": "end"
    },
    "wordplay": {
      "indicator": "",
      "operations": [
        {
          "op": "synonym",
          "input": "In favour of",
          "output": "FOR"
        },
        {
          "op": "synonym",
          "input": "acquiring",
          "output": "GET"
        },
        {
          "op": "concat",
          "input": "FOR+GET",
          "output": "FORGET"
        }
      ]
    },
    "parse": "FOR (in favour of) + GET (acquiring) = FORGET, to overlook."
  },
  {
    "answer": "INKPOT",
    "clueType": "charade",
    "difficulty": 2,
    "clue": "Writing fluid in a vessel, the desk container (6)",
    "def": {
      "text": "desk container",
      "position": "end"
    },
    "wordplay": {
      "indicator": "",
      "operations": [
        {
          "op": "synonym",
          "input": "Writing fluid",
          "output": "INK"
        },
        {
          "op": "synonym",
          "input": "vessel",
          "output": "POT"
        },
        {
          "op": "concat",
          "input": "INK+POT",
          "output": "INKPOT"
        }
      ]
    },
    "parse": "INK (writing fluid) + POT (vessel) = INKPOT, a desk container."
  },
  {
    "answer": "SECRET",
    "clueType": "container",
    "difficulty": 3,
    "clue": "Musical note tucked inside faction, kept hidden (6)",
    "def": {
      "text": "kept hidden",
      "position": "end"
    },
    "wordplay": {
      "indicator": "tucked inside",
      "operations": [
        {
          "op": "inner",
          "input": "Musical note",
          "output": "RE"
        },
        {
          "op": "outer",
          "input": "faction",
          "output": "SECT"
        },
        {
          "op": "insert",
          "input": "RE in SECT",
          "output": "SECRET"
        }
      ]
    },
    "parse": "RE (musical note) inside SECT (faction): SEC-RE-T = SECRET, kept hidden."
  },
  {
    "answer": "PLANET",
    "clueType": "container",
    "difficulty": 3,
    "clue": "Energy held by the factory, a world (6)",
    "def": {
      "text": "world",
      "position": "end"
    },
    "wordplay": {
      "indicator": "held by",
      "operations": [
        {
          "op": "inner",
          "input": "Energy",
          "output": "E"
        },
        {
          "op": "outer",
          "input": "factory",
          "output": "PLANT"
        },
        {
          "op": "insert",
          "input": "E in PLANT",
          "output": "PLANET"
        }
      ]
    },
    "parse": "E (energy) inside PLANT (factory): PLAN-E-T = PLANET, a world."
  },
  {
    "answer": "MARKET",
    "clueType": "container",
    "difficulty": 3,
    "clue": "Vessel held by police force in the bazaar (6)",
    "def": {
      "text": "bazaar",
      "position": "end"
    },
    "wordplay": {
      "indicator": "held by",
      "operations": [
        {
          "op": "inner",
          "input": "Vessel",
          "output": "ARK"
        },
        {
          "op": "outer",
          "input": "police force",
          "output": "MET"
        },
        {
          "op": "insert",
          "input": "ARK in MET",
          "output": "MARKET"
        }
      ]
    },
    "parse": "ARK (vessel) inside MET (police force): M-ARK-ET = MARKET, a bazaar."
  },
  {
    "answer": "BASKET",
    "clueType": "container",
    "difficulty": 3,
    "clue": "Request held by a wager in the hamper (6)",
    "def": {
      "text": "hamper",
      "position": "end"
    },
    "wordplay": {
      "indicator": "held by",
      "operations": [
        {
          "op": "inner",
          "input": "Request",
          "output": "ASK"
        },
        {
          "op": "outer",
          "input": "wager",
          "output": "BET"
        },
        {
          "op": "insert",
          "input": "ASK in BET",
          "output": "BASKET"
        }
      ]
    },
    "parse": "ASK (request) inside BET (wager): B-ASK-ET = BASKET, a hamper."
  },
  {
    "answer": "HAMPER",
    "clueType": "container",
    "difficulty": 3,
    "clue": "Current unit embraced by her, set to hinder (6)",
    "def": {
      "text": "hinder",
      "position": "end"
    },
    "wordplay": {
      "indicator": "embraced by",
      "operations": [
        {
          "op": "inner",
          "input": "Current unit",
          "output": "AMP"
        },
        {
          "op": "outer",
          "input": "her",
          "output": "HER"
        },
        {
          "op": "insert",
          "input": "AMP in HER",
          "output": "HAMPER"
        }
      ]
    },
    "parse": "AMP (current unit) inside HER: H-AMP-ER = HAMPER, to hinder."
  },
  {
    "answer": "WALLET",
    "clueType": "container",
    "difficulty": 3,
    "clue": "Everything inside damp purse (6)",
    "def": {
      "text": "purse",
      "position": "end"
    },
    "wordplay": {
      "indicator": "inside",
      "operations": [
        {
          "op": "inner",
          "input": "Everything",
          "output": "ALL"
        },
        {
          "op": "outer",
          "input": "damp",
          "output": "WET"
        },
        {
          "op": "insert",
          "input": "ALL in WET",
          "output": "WALLET"
        }
      ]
    },
    "parse": "ALL (everything) inside WET (damp): W-ALL-ET = WALLET, a purse."
  },
  {
    "answer": "PARSON",
    "clueType": "hidden",
    "difficulty": 2,
    "clue": "Clergyman seen in cheap arson cases (6)",
    "def": {
      "text": "Clergyman",
      "position": "start"
    },
    "wordplay": {
      "indicator": "seen in",
      "operations": [
        {
          "op": "hidden",
          "input": "cheaP ARSON",
          "output": "PARSON"
        }
      ]
    },
    "parse": "Hidden in cheaP ARSON = PARSON, a clergyman."
  },
  {
    "answer": "ESTATE",
    "clueType": "hidden",
    "difficulty": 2,
    "clue": "Property buried in west at eastern edge (6)",
    "def": {
      "text": "Property",
      "position": "start"
    },
    "wordplay": {
      "indicator": "buried in",
      "operations": [
        {
          "op": "hidden",
          "input": "wEST AT Eastern",
          "output": "ESTATE"
        }
      ]
    },
    "parse": "Hidden in wEST AT Eastern = ESTATE, a property."
  },
  {
    "answer": "DEMEAN",
    "clueType": "hidden",
    "difficulty": 2,
    "clue": "Part of homemade meanness can degrade (6)",
    "def": {
      "text": "degrade",
      "position": "end"
    },
    "wordplay": {
      "indicator": "Part of",
      "operations": [
        {
          "op": "hidden",
          "input": "homemaDE MEANness",
          "output": "DEMEAN"
        }
      ]
    },
    "parse": "Hidden in homemaDE MEANness = DEMEAN, to degrade."
  },
  {
    "answer": "REWARD",
    "clueType": "reversal",
    "difficulty": 2,
    "clue": "Prize drawer knocked back (6)",
    "def": {
      "text": "Prize",
      "position": "start"
    },
    "wordplay": {
      "indicator": "knocked back",
      "operations": [
        {
          "op": "reverse",
          "input": "DRAWER",
          "output": "REWARD"
        }
      ]
    },
    "parse": "DRAWER reversed = REWARD, a prize."
  },
  {
    "answer": "DENIER",
    "clueType": "reversal",
    "difficulty": 2,
    "clue": "One who says no, reined back (6)",
    "def": {
      "text": "One who says no",
      "position": "start"
    },
    "wordplay": {
      "indicator": "back",
      "operations": [
        {
          "op": "reverse",
          "input": "REINED",
          "output": "DENIER"
        }
      ]
    },
    "parse": "REINED reversed = DENIER, one who denies."
  },
  {
    "answer": "REPAID",
    "clueType": "reversal",
    "difficulty": 2,
    "clue": "Settled, having diaper turned over (6)",
    "def": {
      "text": "Settled",
      "position": "start"
    },
    "wordplay": {
      "indicator": "turned over",
      "operations": [
        {
          "op": "reverse",
          "input": "DIAPER",
          "output": "REPAID"
        }
      ]
    },
    "parse": "DIAPER reversed = REPAID, settled a debt."
  },
  {
    "answer": "ANGLER",
    "clueType": "deletion",
    "difficulty": 2,
    "clue": "Beheaded dangler turns out to be a fisherman (6)",
    "def": {
      "text": "fisherman",
      "position": "end"
    },
    "wordplay": {
      "indicator": "Beheaded",
      "operations": [
        {
          "op": "delete",
          "input": "DANGLER − D",
          "output": "ANGLER"
        }
      ]
    },
    "parse": "DANGLER minus first letter D = ANGLER, a fisherman."
  },
  {
    "answer": "EARNED",
    "clueType": "deletion",
    "difficulty": 2,
    "clue": "Merited, having learned and been beheaded (6)",
    "def": {
      "text": "Merited",
      "position": "start"
    },
    "wordplay": {
      "indicator": "beheaded",
      "operations": [
        {
          "op": "delete",
          "input": "LEARNED − L",
          "output": "EARNED"
        }
      ]
    },
    "parse": "LEARNED minus first letter L = EARNED, merited."
  },
  {
    "answer": "PLEASE",
    "clueType": "deletion",
    "difficulty": 2,
    "clue": "Pleased to lose its tail, but still delight (6)",
    "def": {
      "text": "delight",
      "position": "end"
    },
    "wordplay": {
      "indicator": "to lose its tail",
      "operations": [
        {
          "op": "delete",
          "input": "PLEASED − D",
          "output": "PLEASE"
        }
      ]
    },
    "parse": "PLEASED minus last letter D = PLEASE, to delight."
  },
  {
    "answer": "BATTER",
    "clueType": "double-definition",
    "difficulty": 2,
    "clue": "Pound the cricketer (6)",
    "def": {
      "text": "Pound",
      "position": "start"
    },
    "wordplay": {
      "indicator": "",
      "operations": [
        {
          "op": "literal",
          "input": "two definitions",
          "output": "BATTER"
        }
      ]
    },
    "parse": "BATTER = to pound; and a cricketer (batter)."
  },
  {
    "answer": "TENDER",
    "clueType": "double-definition",
    "difficulty": 2,
    "clue": "Gentle, or an offer (6)",
    "def": {
      "text": "Gentle",
      "position": "start"
    },
    "wordplay": {
      "indicator": "",
      "operations": [
        {
          "op": "literal",
          "input": "two definitions",
          "output": "TENDER"
        }
      ]
    },
    "parse": "TENDER = gentle; and an offer (a bid)."
  },
  {
    "answer": "SECOND",
    "clueType": "double-definition",
    "difficulty": 2,
    "clue": "Support a moment (6)",
    "def": {
      "text": "Support",
      "position": "start"
    },
    "wordplay": {
      "indicator": "",
      "operations": [
        {
          "op": "literal",
          "input": "two definitions",
          "output": "SECOND"
        }
      ]
    },
    "parse": "SECOND = to support (a motion); and a moment of time."
  },
  {
    "answer": "MEDDLE",
    "clueType": "homophone",
    "difficulty": 2,
    "clue": "Interfere with award, we hear (6)",
    "def": {
      "text": "Interfere",
      "position": "start"
    },
    "wordplay": {
      "indicator": "we hear",
      "operations": [
        {
          "op": "homophone",
          "input": "MEDAL",
          "output": "MEDDLE"
        }
      ]
    },
    "parse": "MEDDLE sounds like MEDAL (award); means to interfere."
  }
]
